minecraft_mod_manager/__init__.py
minecraft_mod_manager/__main__.py
minecraft_mod_manager/config.py
minecraft_mod_manager/adapters/__init__.py
minecraft_mod_manager/adapters/repo_impl.py
minecraft_mod_manager/adapters/repo_impl_test.py
minecraft_mod_manager/app/__init__.py
minecraft_mod_manager/app/configure/__init__.py
minecraft_mod_manager/app/configure/configure.py
minecraft_mod_manager/app/configure/configure_repo.py
minecraft_mod_manager/app/configure/configure_test.py
minecraft_mod_manager/app/download/__init__.py
minecraft_mod_manager/app/download/download.py
minecraft_mod_manager/app/download/download_repo.py
minecraft_mod_manager/app/download/download_test.py
minecraft_mod_manager/app/install/__init__.py
minecraft_mod_manager/app/install/install.py
minecraft_mod_manager/app/install/install_repo.py
minecraft_mod_manager/app/install/install_test.py
minecraft_mod_manager/app/show/__init__.py
minecraft_mod_manager/app/show/show.py
minecraft_mod_manager/app/show/show_repo.py
minecraft_mod_manager/app/show/show_test.py
minecraft_mod_manager/app/update/__init__.py
minecraft_mod_manager/app/update/update.py
minecraft_mod_manager/app/update/update_repo.py
minecraft_mod_manager/app/update/update_test.py
minecraft_mod_manager/core/__init__.py
minecraft_mod_manager/core/entities/__init__.py
minecraft_mod_manager/core/entities/actions.py
minecraft_mod_manager/core/entities/mod.py
minecraft_mod_manager/core/entities/mod_loaders.py
minecraft_mod_manager/core/entities/sites.py
minecraft_mod_manager/core/entities/version_info.py
minecraft_mod_manager/core/errors/__init__.py
minecraft_mod_manager/core/errors/download_failed.py
minecraft_mod_manager/core/errors/mod_already_exists.py
minecraft_mod_manager/core/errors/mod_file_invalid.py
minecraft_mod_manager/core/errors/mod_not_found_exception.py
minecraft_mod_manager/core/utils/__init__.py
minecraft_mod_manager/core/utils/latest_version_finder.py
minecraft_mod_manager/core/utils/latest_version_finder_test.py
minecraft_mod_manager-1.4.2.dist-info/LICENSE
minecraft_mod_manager-1.4.2.dist-info/METADATA
minecraft_mod_manager-1.4.2.dist-info/WHEEL
minecraft_mod_manager-1.4.2.dist-info/entry_points.txt
minecraft_mod_manager-1.4.2.dist-info/top_level.txt
minecraft_mod_manager-1.4.2.dist-info/RECORD
