Metadata-Version: 2.1
Name: minecraft-mod-manager
Version: 1.4.2
Summary: Download and update Minecraft mods from CurseForge and possibly other places in the future.
Home-page: https://github.com/Senth/minecraft-mod-manager
Author: Matteus Magnusson
Author-email: senth.wallace@gmail.com
License: MIT
Classifier: Development Status :: 5 - Production/Stable
Classifier: License :: OSI Approved :: MIT License
Classifier: Programming Language :: Python :: 3.8
Classifier: Programming Language :: Python :: 3.9
Classifier: Programming Language :: Python :: 3.10
Requires-Python: >=3.8
License-File: LICENSE
Requires-Dist: latest-user-agents
Requires-Dist: requests
Requires-Dist: tealprint (>=0.3.0)
Requires-Dist: toml
